tgram/__init__.py
tgram/bound/__init__.py
tgram/bound/callback_query.py
tgram/bound/chat.py
tgram/bound/chat_join_request.py
tgram/bound/chat_member_updated.py
tgram/bound/chosen_inline_result.py
tgram/bound/inline_query.py
tgram/bound/message.py
tgram/bound/paid_media_purchased.py
tgram/bound/pre_checkout_query.py
tgram/bound/shipping_query.py
tgram/bound/user.py
tgram/client/__init__.py
tgram/client/client.py
tgram/client/dispatcher.py
tgram/decorators/__init__.py
tgram/decorators/on_all.py
tgram/decorators/on_business_connection.py
tgram/decorators/on_business_message.py
tgram/decorators/on_callback_query.py
tgram/decorators/on_channel_post.py
tgram/decorators/on_chat_boost.py
tgram/decorators/on_chat_join_request.py
tgram/decorators/on_chat_member.py
tgram/decorators/on_chosen_inline_result.py
tgram/decorators/on_deleted_business_messages.py
tgram/decorators/on_edited_business_message.py
tgram/decorators/on_edited_channel_post.py
tgram/decorators/on_edited_message.py
tgram/decorators/on_exception.py
tgram/decorators/on_inline_query.py
tgram/decorators/on_message.py
tgram/decorators/on_message_reaction.py
tgram/decorators/on_message_reaction_count.py
tgram/decorators/on_my_chat_member.py
tgram/decorators/on_poll.py
tgram/decorators/on_poll_answer.py
tgram/decorators/on_pre_checkout_query.py
tgram/decorators/on_purchased_paid_media.py
tgram/decorators/on_removed_chat_boost.py
tgram/decorators/on_shipping_query.py
tgram/decorators/outgoing_messages.py
tgram/errors.py
tgram/filters.py
tgram/handlers.py
tgram/methods/__init__.py
tgram/methods/bot/close.py
tgram/methods/bot/delete_my_commands.py
tgram/methods/bot/delete_webhook.py
tgram/methods/bot/get_available_gifts.py
tgram/methods/bot/get_me.py
tgram/methods/bot/get_my_commands.py
tgram/methods/bot/get_my_default_administrator_rights.py
tgram/methods/bot/get_my_description.py
tgram/methods/bot/get_my_name.py
tgram/methods/bot/get_my_short_description.py
tgram/methods/bot/get_my_stars_balance.py
tgram-2.0.3.dist-info/METADATA
tgram-2.0.3.dist-info/WHEEL
tgram-2.0.3.dist-info/licenses/LICENSE
tgram-2.0.3.dist-info/RECORD
