Metadata-Version: 2.4
Name: tgram
Version: 2.0.3
Summary: Tgram is a user-friendly and lightweight Python library that simplifies interaction with the Telegram Bot API. It allows developers to easily create, manage, and automate Telegram bots.
License: MIT
License-File: LICENSE
Author: Zaid
Author-email: zaid@z44d.com
Requires-Python: >=3.10
Classifier: License :: OSI Approved :: MIT License
Classifier: Programming Language :: Python :: 3
Classifier: Programming Language :: Python :: 3.10
Classifier: Programming Language :: Python :: 3.11
Classifier: Programming Language :: Python :: 3.12
Classifier: Programming Language :: Python :: 3.13
Classifier: Programming Language :: Python :: 3.14
Requires-Dist: aiohttp (>=3.10.11)
Requires-Dist: certifi (>=2024.12.14)
